csvise-1.2.1.dist-info/licenses/LICENSE
csvtools/__init__.py
csvtools/__main__.py
csvtools/cleaning.py
csvtools/cleaning_ops.py
csvtools/cli.py
csvtools/config.py
csvtools/delimiter.py
csvtools/formatter.py
csvtools/rich_analysis.py
csvtools/rich_formatter.py
csvtools/statistics.py
csvtools/types.py
csvtools/utils.py
csvise-1.2.1.dist-info/METADATA
csvise-1.2.1.dist-info/WHEEL
csvise-1.2.1.dist-info/entry_points.txt
csvise-1.2.1.dist-info/top_level.txt
csvise-1.2.1.dist-info/RECORD
