Metadata-Version: 2.4
Name: csvise
Version: 1.2.1
Summary: CLI Tools for Tabular Data - CSV analysis, validation, and beautiful display
Home-page: https://github.com/rawsabsaid/csvise-cli-tool
Author: Rawsab Said
Author-email: Rawsab Said <rawsab04@gmail.com>
Maintainer-email: Rawsab Said <rawsab04@gmail.com>
License-Expression: MIT
Project-URL: Homepage, https://github.com/rawsabsaid/csvise-cli-tool
Project-URL: Documentation, https://github.com/rawsabsaid/csvise-cli-tool#readme
Project-URL: Repository, https://github.com/rawsabsaid/csvise-cli-tool
Project-URL: Bug Tracker, https://github.com/rawsabsaid/csvise-cli-tool/issues
Project-URL: Source Code, https://github.com/rawsabsaid/csvise-cli-tool
Keywords: csv,cli,data-analysis,validation,table,rich,formatting
Classifier: Development Status :: 4 - Beta
Classifier: Intended Audience :: Developers
Classifier: Intended Audience :: Science/Research
Classifier: Operating System :: OS Independent
Classifier: Programming Language :: Python :: 3
Classifier: Programming Language :: Python :: 3.7
Classifier: Programming Language :: Python :: 3.8
Classifier: Programming Language :: Python :: 3.9
Classifier: Programming Language :: Python :: 3.10
Classifier: Programming Language :: Python :: 3.11
Classifier: Programming Language :: Python :: 3.12
Classifier: Topic :: Scientific/Engineering :: Information Analysis
Classifier: Topic :: Software Development :: Libraries :: Python Modules
Classifier: Topic :: Text Processing :: Filters
Classifier: Topic :: Utilities
Requires-Python: >=3.7
License-File: LICENSE
Requires-Dist: click>=8.0.0
Requires-Dist: rich>=13.0.0
Provides-Extra: dev
Requires-Dist: pytest>=7.0.0; extra == "dev"
Requires-Dist: pytest-cov>=4.0.0; extra == "dev"
Requires-Dist: black>=22.0.0; extra == "dev"
Requires-Dist: flake8>=5.0.0; extra == "dev"
Requires-Dist: mypy>=1.0.0; extra == "dev"
Requires-Dist: pre-commit>=2.20.0; extra == "dev"
Dynamic: author
Dynamic: home-page
Dynamic: license-file
Dynamic: requires-python
